{
  "heroSlides": [
    "/assets/images/venues/Screenshot 2026-03-23 081552.png",
    "/assets/images/venues/Screenshot 2026-03-23 081608.png",
    "/assets/images/venues/Screenshot 2026-03-23 081623.png",
    "/assets/images/venues/Screenshot 2026-03-23 081645.png",
    "/assets/images/venues/unnamed (2).webp"
  ],
  "ceremony": {
    "name": "The Grounds Events Place",
    "address": "Sitio Gulod, Sapang Palay, Proper",
    "city": "SJDM",
    "state": "Bulacan",
    "zip": "3024, Philippines",
    "time": "3:30 PM",
    "googleMapsUrl": "https://share.google/FgjOXlmAYOgWZO8VZ",
    "directionsUrl": "https://share.google/FgjOXlmAYOgWZO8VZ",
    "image": "/assets/images/venues/ceremony.jpg"
  },
  "reception": {
    "name": "The Grounds Events Place",
    "address": "Sitio Gulod, Sapang Palay, Proper",
    "city": "SJDM",
    "state": "Bulacan",
    "zip": "3024, Philippines",
    "time": "6:00 PM",
    "landmark": "Main Hall",
    "googleMapsUrl": "https://share.google/FgjOXlmAYOgWZO8VZ",
    "directionsUrl": "https://share.google/FgjOXlmAYOgWZO8VZ",
    "image": "/assets/images/venues/reception.jpg"
  }
} 